dupe/__init__.py
dupe/dupe.py
dupe-0.0.2.dist-info/WHEEL
dupe-0.0.2.dist-info/METADATA
dupe-0.0.2.dist-info/RECORD
