Metadata-Version: 2.1
Name: dupe
Version: 0.0.2
Summary: Find duplicate files
Author: Damon Allison
Author-email: damon@damonallison.com
Requires-Python: >=3.9,<4.0
Classifier: Programming Language :: Python :: 3
Classifier: Programming Language :: Python :: 3.9
